<TaskList Name="20 - Wayrest Mudcrab farm">
  <Loops>1</Loops>
  <Task>REPEAT LOOP: 99999</Task>
  <Task>Start Patrol: 20 - Wayrest Mudcrab farm to vendor,0,1</Task>
  <Task>Pause: 30000</Task>
  <Task>Goto Waypoint: 2317.78,2425.27,134.73</Task>
  <Task>Target NPC: Brazzideh</Task>
  <Task>Pause: 1500</Task>
  <Task>Press Key(s): E, 300</Task>
  <Task>Pause: 10000</Task>
  <Task>Press Key(s): E, 300</Task>
  <Task>Pause: 5000</Task>
  <Task>Press Key(s): X, 2000</Task>
  <Task>Pause: 3000</Task>
  <Task>Press Key(s): E, 2000</Task>
  <Task>Pause: 2000</Task>
  <Task>Press Key(s): ESCAPE, 1000</Task>
  <Task>Pause: 1000</Task>
  <Task>Target NPC: Brazzideh</Task>
  <Task>Pause: 1500</Task>
  <Task>Press Key(s): E, 300</Task>
  <Task>Pause: 10000</Task>
  <Task>Press Key(s): E, 300</Task>
  <Task>Pause: 5000</Task>
  <Task>Press Key(s): X, 2000</Task>
  <Task>Pause: 3000</Task>
  <Task>Press Key(s): E, 2000</Task>
  <Task>Pause: 2000</Task>
  <Task>Press Key(s): ESCAPE, 1000</Task>
  <Task>Pause: 1000</Task>
  <Task>Start Patrol: 20 - Wayrest Mudcrab farming,0,6</Task>
  <Task>END REPEAT LOOP</Task>
</TaskList>